Workbook

Sheet FSM Forecast
C2: ="Financial Statement Model for "&D5 -> Financial Statement Model for Micron
C3: $ in millions except per share
C5: Company name | D5: Micron
C6: Ticker | D6: MU
C7: Circ break 1=off, 0=on | D7: 1
C8: Latest closing share price date | D8: 46168
C9: Latest closing share price | D9: 895.88
C10: Latest fiscal year end date | D10: 45897
C11: Shares outstanding (millions) | D11: 1122.466
C12: Active Case | D12: Base Case
B14: x | C14: INCOME STATEMENT
C15: Fiscal year | D15: =E15-1 -> 2023 | E15: =F15-1 -> 2024 | F15: 2025 | G15: 2026 | H15: =G15+1 -> 2027 | I15: =H15+1 -> 2028 | J15: =I15+1 -> 2029 | K15: =J15+1 -> 2030
C16: Fiscal year end date | D16: =DATE(2024,8,29)-364 -> 45169 | E16: =DATE(2025,8,28)-364 -> 45533 | F16: =D10 -> 45897 | G16: =DATE(2025,8,28)+364 -> 46261 | H16: =DATE(2026,8,27)+364 -> 46625 | I16: =DATE(2027,8,26)+371 -> 46996 | J16: =DATE(2028,8,31)+364 -> 47360 | K16: =DATE(2029,8,30)+364 -> 47724
C18: Revenue | D18: 15540 | E18: 25111 | F18: 37378 | G18: =F18*(1+G39) -> 111252.28 | H18: =G18*(1+H39) -> 158866.68 | I18: =H18*(1+I39) -> 159891.88 | J18: =I18*(1+J39) -> 149898.64 | K18: =J18*(1+K39) -> 161890.53
C19: Cost of sales (enter as -) | D19: -16956 | E19: -19498 | F19: -22505 | G19: =G20-G18 -> -27813.071 | H19: =H20-H18 -> -31773.336 | I19: =I20-I18 -> -55962.157 | J19: =J20-J18 -> -67454.386 | K19: =K20-K18 -> -80945.263
C20: Gross Profit | D20: =SUM(D18:D19) -> -1416 | E20: =SUM(E18:E19) -> 5613 | F20: =SUM(F18:F19) -> 14873 | G20: =G18*G40 -> 83439.213 | H20: =H18*H40 -> 127093.35 | I20: =I18*I40 -> 103929.72 | J20: =J18*J40 -> 82444.25 | K20: =K18*K40 -> 80945.263
C21: Research & development (enter as -) | D21: -3114 | E21: -3430 | F21: -3798 | G21: =-G18*G41 -> -9790.201 | H21: =-H18*H41 -> -14679.281 | I21: =-I18*I41 -> -14710.053 | J21: =-J18*J41 -> -13790.674 | K21: =-K18*K41 -> -14893.928
C22: Selling, general & administrative (enter as -) | D22: -920 | E22: -1129 | F22: -1205 | G22: =-(G18*G42) -> -2781.3071 | H22: =-(H18*H42) -> -3971.667 | I22: =-(I18*I42) -> -3997.297 | J22: =-(J18*J42) -> -3747.4659 | K22: =-(K18*K42) -> -4047.2632
C23: Restructuring & asset impairments | D23: -171 | E23: -1 | F23: -39 | G23: 0 | H23: 0 | I23: 0 | J23: 0 | K23: 0
C24: Other operating income (expense), net | D24: -124 | E24: 251 | F24: -61 | G24: 0 | H24: 0 | I24: 0 | J24: 0 | K24: 0
C25: Operating profit (EBIT) | D25: =SUM(D20:D24) -> -5745 | E25: =SUM(E20:E24) -> 1304 | F25: =SUM(F20:F24) -> 9770 | G25: =SUM(G20:G22) -> 70867.705 | H25: =SUM(H20:H22) -> 108442.4 | I25: =SUM(I20:I22) -> 85222.371 | J25: =SUM(J20:J22) -> 64906.109 | K25: =SUM(K20:K22) -> 62004.072
C26: Interest income | D26: 468 | E26: 529 | F26: 496 | G26: =G170 -> 914.5455 | H26: =H170 -> 2613.4693 | I26: =I170 -> 5083.8373 | J26: =J170 -> 7288.7902 | K26: =K170 -> 9190.9367
C27: Interest expense (enter as -) | D27: -388 | E27: -562 | F27: -477 | G27: =-G153 -> -619.8925 | H27: =-H153 -> -423.3925 | I27: =-I153 -> -318.3925 | J27: =-J153 -> -213.3925 | K27: =-K153 -> -108.3925
C28: Other expense, net (enter as -) | D28: 7 | E28: -31 | F28: -135 | G28: =F28 -> -135 | H28: =G28 -> -135 | I28: =H28 -> -135 | J28: =I28 -> -135 | K28: =J28 -> -135
C29: Pretax profit | D29: =SUM(D25:D28) -> -5658 | E29: =SUM(E25:E28) -> 1240 | F29: =SUM(F25:F28) -> 9654 | G29: =SUM(G25:G28) -> 71027.358 | H29: =SUM(H25:H28) -> 110497.47 | I29: =SUM(I25:I28) -> 89852.816 | J29: =SUM(J25:J28) -> 71846.507 | K29: =SUM(K25:K28) -> 70951.616
C30: Taxes (enter expense as -) | D30: -177 | E30: -451 | F30: -1124 | G30: =-G29*G44 -> -11719.514 | H30: =-H29*H44 -> -18232.083 | I30: =-I29*I44 -> -14825.715 | J30: =-J29*J44 -> -11854.674 | K30: =-K29*K44 -> -11707.017
C31: Net income | D31: =SUM(D29:D30) -> -5835 | E31: =SUM(E29:E30) -> 789 | F31: =SUM(F29:F30) -> 8530 | G31: =SUM(G29:G30) -> 59307.844 | H31: =SUM(H29:H30) -> 92265.391 | I31: =SUM(I29:I30) -> 75027.101 | J31: =SUM(J29:J30) -> 59991.833 | K31: =SUM(K29:K30) -> 59244.599
C33: Depreciation & amortization | D33: 7756 | E33: 7780 | F33: 8352 | G33: =G117 -> 15040.649 | H33: =H117 -> 22612.893 | I33: =I117 -> 27082.589 | J33: =J117 -> 29051.36 | K33: =K117 -> 31044.614
C34: EBITDA | D34: =D33+D25 -> 2011 | E34: =E33+E25 -> 9084 | F34: =F33+F25 -> 18122 | G34: =G33+G25 -> 85908.354 | H34: =H33+H25 -> 131055.29 | I34: =I33+I25 -> 112304.96 | J34: =J33+J25 -> 93957.469 | K34: =K33+K25 -> 93048.686
C35: Stock based compensation | D35: 596 | E35: 833 | F35: 972 | G35: =F35*(1+G43) -> 1069.2 | H35: =G35*(1+H43) -> 1176.12 | I35: =H35*(1+I43) -> 1293.732 | J35: =I35*(1+J43) -> 1423.1052 | K35: =J35*(1+K43) -> 1565.4157
C36: Adjusted EBITDA | D36: =SUM(D34:D35) -> 2607 | E36: =SUM(E34:E35) -> 9917 | F36: =SUM(F34:F35) -> 19094 | G36: =SUM(G34:G35) -> 86977.554 | H36: =SUM(H34:H35) -> 132231.41 | I36: =SUM(I34:I35) -> 113598.69 | J36: =SUM(J34:J35) -> 95380.574 | K36: =SUM(K34:K35) -> 94614.102
C38: Growth rates & margins
C39: Revenue growth | E39: =E18/D18-1 -> 0.61589447 | F39: =F18/E18-1 -> 0.48851101 | G39: =G220 -> 1.9764108 | H39: =H220 -> 0.42798579 | I39: =I220 -> 0.0064531855 | J39: =J220 -> -0.0625 | K39: =K220 -> 0.08
C40: Gross profit margin | D40: =D20/D18 -> -0.091119691 | E40: =E20/E18 -> 0.22352754 | F40: =F20/F18 -> 0.39790786 | G40: =G221 -> 0.75 | H40: =H221 -> 0.8 | I40: =I221 -> 0.65 | J40: =J221 -> 0.55 | K40: =K221 -> 0.5
C41: R&D % of sales | D41: =-(D21/D18) -> 0.2003861 | E41: =-(E21/E18) -> 0.13659352 | F41: =-(F21/F18) -> 0.10161057 | G41: =G222 -> 0.088 | H41: =H222 -> 0.0924 | I41: =I222 -> 0.092 | J41: =J222 -> 0.092 | K41: =K222 -> 0.092
C42: SG&A % of sales | D42: =-(D22/D18) -> 0.059202059 | E42: =-(E22/E18) -> 0.044960376 | F42: =-(F22/F18) -> 0.032238215 | G42: =G223 -> 0.025 | H42: =H223 -> 0.025 | I42: =I223 -> 0.025 | J42: =J223 -> 0.025 | K42: =K223 -> 0.025
C43: SBC Increase | E43: =(E35/D35)-1 -> 0.39765101 | F43: =(F35/E35)-1 -> 0.16686675 | G43: 0.1 | H43: 0.1 | I43: 0.1 | J43: 0.1 | K43: 0.1
C44: Tax rate | D44: N/M | E44: =-E30/E29 -> 0.36370968 | F44: =-F30/F29 -> 0.11642842 | G44: 0.165 | H44: 0.165 | I44: 0.165 | J44: 0.165 | K44: 0.165
B46: x | C46: BALANCE SHEET
C47: Fiscal year | E47: =F47-1 -> 2024 | F47: 2025 | G47: 2026 | H47: =G47+1 -> 2027 | I47: =H47+1 -> 2028 | J47: =I47+1 -> 2029 | K47: =J47+1 -> 2030
C48: Fiscal year end date | E48: =DATE(2025,8,28)-364 -> 45533 | F48: =D10 -> 45897 | G48: =DATE(2025,8,28)+364 -> 46261 | H48: =DATE(2026,8,27)+364 -> 46625 | I48: =DATE(2027,8,26)+371 -> 46996 | J48: =DATE(2028,8,31)+364 -> 47360 | K48: =DATE(2029,8,30)+364 -> 47724
C49: Cash & equivalents, ST and LT marketable securities | E49: =7041+1065+1046 -> 9152 | F49: =9642+665+1629 -> 11936 | G49: =F49+G101 -> 33791.275 | H49: =G49+H101 -> 96882.192 | I49: =H49+I101 -> 157309.67 | J49: =I49+J101 -> 207129.84 | K49: =J49+K101 -> 252417
C50: Accounts receivable | E50: 6615 | F50: 9265 | G50: =F50*(1+G39) -> 27576.446 | H50: =G50*(1+H39) -> 39378.774 | I50: =H50*(1+I39) -> 39632.892 | J50: =I50*(1+J39) -> 37155.837 | K50: =J50*(1+K39) -> 40128.304
C51: Inventories | E51: 8875 | F51: 8355 | G51: =(F51)*(G19/F19) -> 10325.626 | H51: =(G51)*(H19/G19) -> 11795.878 | I51: =(H51)*(I19/H19) -> 20775.998 | J51: =(I51)*(J19/I19) -> 25042.497 | K51: =(J51)*(K19/J19) -> 30050.996
C52: Other current assets | E52: 776 | F52: 914 | G52: =F52*(1+G39) -> 2720.4395 | H52: =G52*(1+H39) -> 3884.749 | I52: =H52*(1+I39) -> 3909.818 | J52: =I52*(1+J39) -> 3665.4544 | K52: =J52*(1+K39) -> 3958.6907
C53: Property, plant & equipment | E53: 39749 | F53: 46590 | G53: =G110 -> 57716.23 | H53: =H110 -> 71321.778 | I53: =I110 -> 84439.054 | J53: =J110 -> 95556.33 | K53: =K110 -> 104673.61
C54: Operating lease right-of-use assets | E54: 645 | F54: 736 | G54: =$F$54 -> 736 | H54: =G54 -> 736 | I54: =H54 -> 736 | J54: =I54 -> 736 | K54: =J54 -> 736
C55: Intangible assets | E55: 416 | F55: 453 | G55: =F55 -> 453 | H55: =G55 -> 453 | I55: =H55 -> 453 | J55: =I55 -> 453 | K55: =J55 -> 453
C56: Deferred tax assets | E56: 520 | F56: 616 | G56: =F56 -> 616 | H56: =G56 -> 616 | I56: =H56 -> 616 | J56: =I56 -> 616 | K56: =J56 -> 616
C57: Goodwill | E57: 1150 | F57: 1150 | G57: =F57 -> 1150 | H57: =G57 -> 1150 | I57: =H57 -> 1150 | J57: =I57 -> 1150 | K57: =J57 -> 1150
C58: Other non current assets | E58: 1518 | F58: 2783 | G58: =F58*(1+G39) -> 8283.3514 | H58: =G58*(1+H39) -> 11828.508 | I58: =H58*(1+I39) -> 11904.84 | J58: =I58*(1+J39) -> 11160.787 | K58: =J58*(1+K39) -> 12053.65
C59: Total assets | E59: =SUM(E49:E58) -> 69416 | F59: =SUM(F49:F58) -> 82798 | G59: =SUM(G49:G58) -> 143368.37 | H59: =SUM(H49:H58) -> 238046.88 | I59: =SUM(I49:I58) -> 320927.27 | J59: =SUM(J49:J58) -> 382665.74 | K59: =SUM(K49:K58) -> 446237.24
C61: Accounts payable | E61: 7299 | F61: 9649 | G61: =F61*(G19/F19) -> 11924.831 | H61: =G61*(H19/G19) -> 13622.791 | I61: =H61*(I19/H19) -> 23993.728 | J61: =I61*(J19/I19) -> 28921.012 | K61: =J61*(K19/J19) -> 34705.214
C62: Other current liabilities | E62: 1518 | F62: 1245 | G62: =F62*(1+G39) -> 3705.6315 | H62: =G62*(1+H39) -> 5291.5891 | I62: =H62*(1+I39) -> 5325.7367 | J62: =I62*(1+J39) -> 4992.8782 | K62: =J62*(1+K39) -> 5392.3085
C63: Commercial paper / revolver | E63: 431 | F63: 560 | G63: =G146 -> 50 | H63: =H146 -> 50 | I63: =I146 -> 50 | J63: =J146 -> 50 | K63: =K146 -> 50
C64: Long term debt (includes current portion) | E64: 12966 | F64: 14017 | G64: =G163 -> 9017 | H64: =H163 -> 7017 | I64: =I163 -> 5017 | J64: =J163 -> 3017 | K64: =K163 -> 1017
C65: Noncurrent operating lease liabilities | E65: 610 | F65: 701 | G65: =F65 -> 701 | H65: =G65 -> 701 | I65: =H65 -> 701 | J65: =I65 -> 701 | K65: =J65 -> 701
C66: Noncurrent unearned government incentives | E66: 550 | F66: 1018 | G66: =F66 -> 1018 | H66: =G66 -> 1018 | I66: =H66 -> 1018 | J66: =I66 -> 1018 | K66: =J66 -> 1018
C67: Other non current liabilities | E67: 911 | F67: 1443 | G67: =F67*(1+G39) -> 4294.9609 | H67: =G67*(1+H39) -> 6133.1431 | I67: =H67*(1+I39) -> 6172.7214 | J67: =I67*(1+J39) -> 5786.9263 | K67: =J67*(1+K39) -> 6249.8804
C68: Total liabilities | E68: =SUM(E61:E67) -> 24285 | F68: =SUM(F61:F67) -> 28633 | G68: =SUM(G61:G67) -> 30711.423 | H68: =SUM(H61:H67) -> 33833.524 | I68: =SUM(I61:I67) -> 42278.186 | J68: =SUM(J61:J67) -> 44486.816 | K68: =SUM(K61:K67) -> 49133.403
C70: Common stock | E70: 125 | F70: 127 | G70: =F70 -> 127 | H70: =G70 -> 127 | I70: =H70 -> 127 | J70: =I70 -> 127 | K70: =J70 -> 127
C71: Additional Capital | E71: 12115 | F71: 13339 | G71: =F71+G35 -> 14408.2 | H71: =G71+H35 -> 15584.32 | I71: =H71+I35 -> 16878.052 | J71: =I71+J35 -> 18301.157 | K71: =J71+K35 -> 19866.573
C72: Retained earnings | E72: 40877 | F72: 48583 | G72: =G130 -> 106005.74 | H72: =H130 -> 196386.03 | I72: =I130 -> 269528.04 | J72: =J130 -> 327634.77 | K72: =K130 -> 384994.27
C73: Treasury Stock | E73: -7852 | F73: -7852 | G73: -7852 | H73: -7852 | I73: -7852 | J73: -7852 | K73: -7852
C74: Other comprehensive income | E74: -134 | F74: -32 | G74: =F74 -> -32 | H74: =G74 -> -32 | I74: =H74 -> -32 | J74: =I74 -> -32 | K74: =J74 -> -32
C75: Total equity | E75: =SUM(E70:E74) -> 45131 | F75: =SUM(F70:F74) -> 54165 | G75: =SUM(G70:G74) -> 112656.94 | H75: =SUM(H70:H74) -> 204213.35 | I75: =SUM(I70:I74) -> 278649.09 | J75: =SUM(J70:J74) -> 338178.93 | K75: =SUM(K70:K74) -> 397103.84
C77: Balance check | E77: =E59-E68-E75 -> 0 | F77: =F59-F68-F75 -> 0 | G77: =G59-G68-G75 -> 0 | H77: =H59-H68-H75 -> 0 | I77: =I59-I68-I75 -> 2.5954796e-07 | J77: =J59-J68-J75 -> 3.2993266e-06 | K77: =K59-K68-K75 -> 3.6537589e-05
B79: x | C79: CASH FLOW STATEMENT
C80: Fiscal year | G80: 2026 | H80: =G80+1 -> 2027 | I80: =H80+1 -> 2028 | J80: =I80+1 -> 2029 | K80: =J80+1 -> 2030
C81: Fiscal year end date | G81: =DATE(2025,8,28)+364 -> 46261 | H81: =DATE(2026,8,27)+364 -> 46625 | I81: =DATE(2027,8,26)+371 -> 46996 | J81: =DATE(2028,8,31)+364 -> 47360 | K81: =DATE(2029,8,30)+364 -> 47724
C83: Net income | G83: =G31 -> 59307.844 | H83: =H31 -> 92265.391 | I83: =I31 -> 75027.101 | J83: =J31 -> 59991.833 | K83: =K31 -> 59244.599
C84: Depreciation and amortization | G84: =G33 -> 15040.649 | H84: =H33 -> 22612.893 | I84: =I33 -> 27082.589 | J84: =J33 -> 29051.36 | K84: =K33 -> 31044.614
C85: Stock based compensation | G85: =G35 -> 1069.2 | H85: =H35 -> 1176.12 | I85: =I35 -> 1293.732 | J85: =J35 -> 1423.1052 | K85: =K35 -> 1565.4157
C86: Decreases / (Increases) in working capital assets | G86: =SUM(F50:F52)-SUM(G50:G52) -> -22088.512 | H86: =SUM(G50:G52)-SUM(H50:H52) -> -14436.889 | I86: =SUM(H50:H52)-SUM(I50:I52) -> -9259.3075 | J86: =SUM(I50:I52)-SUM(J50:J52) -> -1545.0801 | K86: =SUM(J50:J52)-SUM(K50:K52) -> -8274.2027
C87: Increases / (Decreases) in working capital liabilities | G87: =SUM(G61:G62)-SUM(F61:F62) -> 4736.4626 | H87: =SUM(H61:H62)-SUM(G61:G62) -> 3283.918 | I87: =SUM(I61:I62)-SUM(H61:H62) -> 10405.084 | J87: =SUM(J61:J62)-SUM(I61:I62) -> 4594.4249 | K87: =SUM(K61:K62)-SUM(J61:J62) -> 6183.6326
C88: Other non current assets | G88: =-G122 -> -5667.2298 | H88: =-H122 -> -3763.5984 | I88: =-I122 -> -276.1964 | J88: =-J122 -> 575.41651 | K88: =-K122 -> -1054.7535
C89: Other non current liabilities | G89: =G67-F67 -> 2851.9609 | H89: =H67-G67 -> 1838.1822 | I89: =I67-H67 -> 39.57831 | J89: =J67-I67 -> -385.79509 | K89: =K67-J67 -> 462.9541
C90: Cash from operating activities | G90: =SUM(G83:G89) -> 55250.375 | H90: =SUM(H83:H89) -> 102976.02 | I90: =SUM(I83:I89) -> 104312.58 | J90: =SUM(J83:J89) -> 93705.265 | K90: =SUM(K83:K89) -> 89172.26
C92: Capital expenditures | G92: =-G108 -> -26000 | H92: =-H108 -> -36000 | I92: =-I108 -> -40000 | J92: =-J108 -> -40000 | K92: =-K108 -> -40000
C93: Cash from investing activities | G93: =G92 -> -26000 | H93: =H92 -> -36000 | I93: =I92 -> -40000 | J93: =J92 -> -40000 | K93: =K92 -> -40000
C95: Long term debt | G95: =G64-F64 -> -5000 | H95: =H64-G64 -> -2000 | I95: =I64-H64 -> -2000 | J95: =J64-I64 -> -2000 | K95: =K64-J64 -> -2000
C96: Revolver | G96: =G63-F63 -> -510 | H96: =H63-G63 -> 0 | I96: =I63-H63 -> 0 | J96: =J63-I63 -> 0 | K96: =K63-J63 -> 0
C97: Share repurchases | G97: =G129 -> -1200 | H97: =H129 -> -1200 | I97: =I129 -> -1200 | J97: =J129 -> -1200 | K97: =K129 -> -1200
C98: Common dividends | G98: =G128 -> -685.1 | H98: =H128 -> -685.1 | I98: =I128 -> -685.1 | J98: =J128 -> -685.1 | K98: =K128 -> -685.1
C99: Cash from financing activities | G99: =SUM(G95:G98) -> -7395.1 | H99: =SUM(H95:H98) -> -3885.1 | I99: =SUM(I95:I98) -> -3885.1 | J99: =SUM(J95:J98) -> -3885.1 | K99: =SUM(K95:K98) -> -3885.1
C101: Net change in cash during period | G101: =G99+G90+G93 -> 21855.275 | H101: =H99+H90+H93 -> 63090.917 | I101: =I99+I90+I93 -> 60427.481 | J101: =J99+J90+J93 -> 49820.165 | K101: =K99+K90+K93 -> 45287.16
B103: x | C103: PROPERTY, PLANT & EQUIPMENT
C104: Fiscal year | D104: =E104-1 -> 2023 | E104: =F104-1 -> 2024 | F104: 2025 | G104: 2026 | H104: =G104+1 -> 2027 | I104: =H104+1 -> 2028 | J104: =I104+1 -> 2029 | K104: =J104+1 -> 2030
C105: Fiscal year end date | D105: =DATE(2024,8,29)-364 -> 45169 | E105: =DATE(2025,8,28)-364 -> 45533 | F105: =D10 -> 45897 | G105: =DATE(2025,8,28)+364 -> 46261 | H105: =DATE(2026,8,27)+364 -> 46625 | I105: =DATE(2027,8,26)+371 -> 46996 | J105: =DATE(2028,8,31)+364 -> 47360 | K105: =DATE(2029,8,30)+364 -> 47724
C107: Beginning of period | G107: =F110 -> 46590 | H107: =G110 -> 57716.23 | I107: =H110 -> 71321.778 | J107: =I110 -> 84439.054 | K107: =J110 -> 95556.33
C108: Plus: Capital expenditures | D108: 7680 | E108: 8390 | F108: 15860 | G108: 26000 | H108: 36000 | I108: 40000 | J108: 40000 | K108: 40000
C109: Less: Depreciation | D109: -7670 | E109: -7700 | F109: -8280 | G109: =-(G108*G112) -> -14873.77 | H109: =-(H108*H112) -> -22394.451 | I109: =-(I108*I112) -> -26882.724 | J109: =-(J108*J112) -> -28882.724 | K109: =-(K108*K112) -> -30882.724
C110: End of period | E110: =E53 -> 39749 | F110: =F53 -> 46590 | G110: =SUM(G107:G109) -> 57716.23 | H110: =SUM(H107:H109) -> 71321.778 | I110: =SUM(I107:I109) -> 84439.054 | J110: =SUM(J107:J109) -> 95556.33 | K110: =SUM(K107:K109) -> 104673.61
L111: Step
C112: D&A related to PP&E as a % of capex | D112: =-(D109/D108) -> 0.99869792 | E112: =-(E109/E108) -> 0.91775924 | F112: =-(F109/F108) -> 0.5220681 | G112: =F112+$L$112 -> 0.5720681 | H112: =G112+$L$112 -> 0.6220681 | I112: =H112+$L$112 -> 0.6720681 | J112: =I112+$L$112 -> 0.7220681 | K112: =J112+$L$112 -> 0.7720681 | L112: 0.05
B114: x | C114: IMPUTING TOTAL DEPRECIATION & AMORTIZATION
C115: D&A not related to PP&E | D115: =D117+D109 -> 86 | E115: =E117+E109 -> 80 | F115: =F117+F109 -> 72 | G115: =G116*G18 -> 166.87843 | H115: =H116*H18 -> 218.44169 | I115: =I116*I18 -> 199.86485 | J115: =J116*J18 -> 168.63597 | K115: =K116*K18 -> 161.89053 | L115: Step
C116: as % of revenue | D116: =D115/D18 -> 0.0055341055 | E116: =E115/E18 -> 0.0031858548 | F116: =F115/F18 -> 0.0019262668 | G116: 0.0015 | H116: =G116-$L$116 -> 0.001375 | I116: =H116-$L$116 -> 0.00125 | J116: =I116-$L$116 -> 0.001125 | K116: =J116-$L$116 -> 0.001 | L116: 0.000125
C117: Depreciation & Amortization - Total | D117: =D33 -> 7756 | E117: =E33 -> 7780 | F117: =F33 -> 8352 | G117: =-(G109-G115) -> 15040.649 | H117: =-(H109-H115) -> 22612.893 | I117: =-(I109-I115) -> 27082.589 | J117: =-(J109-J115) -> 29051.36 | K117: =-(K109-K115) -> 31044.614
C119: OTHER NON-CURRENT ASSETS
...

Sheet Revenue Build
C2: Price / volume build
C3: Fiscal year | E3: 2024 | F3: 2025 | G3: 2026 | H3: =G3+1 -> 2027 | I3: =H3+1 -> 2028 | J3: =I3+1 -> 2029 | K3: =J3+1 -> 2030
C4: Fiscal year end date | E4: =DATE(2025,8,28)-364 -> 45533 | F4: ='FSM Forecast'!D10 -> 45897 | G4: =DATE(2025,8,28)+364 -> 46261 | H4: =DATE(2026,8,27)+364 -> 46625 | I4: =DATE(2027,8,26)+371 -> 46996 | J4: =DATE(2028,8,31)+364 -> 47360 | K4: =DATE(2029,8,30)+364 -> 47724
C5: Revenue by product
C6: Core products
C8: DRAM | E8: 17600 | F8: 28580 | G8: =F8*(1+G22) -> 88269.33 | H8: =G8*(1+H22) -> 127107.84 | I8: =H8*(1+I22) -> 128887.34 | J8: =I8*(1+J22) -> 120831.89 | K8: =J8*(1+K22) -> 130498.44
C9: NAND | E9: 7230 | F9: 8500 | G9: =F9*(1+G23) -> 22100 | H9: =G9*(1+H23) -> 30498 | I9: =H9*(1+I23) -> 29735.55 | J9: =I9*(1+J23) -> 27877.078 | K9: =J9*(1+K23) -> 30107.244
C10: Total Revenue | E10: =SUM(E8:E9) -> 24830 | F10: =SUM(F8:F9) -> 37080 | G10: =SUM(G8:G9) -> 110369.33 | H10: =SUM(H8:H9) -> 157605.84 | I10: =SUM(I8:I9) -> 158622.89 | J10: =SUM(J8:J9) -> 148708.96 | K10: =SUM(K8:K9) -> 160605.68
C11: % growth | F11: =F10/E10-1 -> 0.49335481 | G11: =G10/F10-1 -> 1.9765191 | H11: =H10/G10-1 -> 0.42798579 | I11: =I10/H10-1 -> 0.0064531855 | J11: =J10/I10-1 -> -0.0625 | K11: =K10/J10-1 -> 0.08
C13: Bit Demand Growth
C14: DRAM | G14: 0.45 | H14: 0.2 | I14: 0.3 | J14: 0.25 | K14: 0.2
C15: NAND | G15: 0.3 | H15: 0.2 | I15: 0.3 | J15: 0.25 | K15: 0.2
C17: Average Selling Price Change
C18: DRAM | G18: 1.13 | H18: 0.2 | I18: -0.22 | J18: -0.25 | K18: -0.1
C19: NAND | G19: 1 | H19: 0.15 | I19: -0.25 | J19: -0.25 | K19: -0.1
C21: Revenue Growth
C22: DRAM | G22: =(1+G14)*(1+G18)-1 -> 2.0885 | H22: =(1+H14)*(1+H18)-1 -> 0.44 | I22: =(1+I14)*(1+I18)-1 -> 0.014 | J22: =(1+J14)*(1+J18)-1 -> -0.0625 | K22: =(1+K14)*(1+K18)-1 -> 0.08
C23: NAND | G23: =(1+G15)*(1+G19)-1 -> 1.6 | H23: =(1+H15)*(1+H19)-1 -> 0.38 | I23: =(1+I15)*(1+I19)-1 -> -0.025 | J23: =(1+J15)*(1+J19)-1 -> -0.0625 | K23: =(1+K15)*(1+K19)-1 -> 0.08

Sheet DCF
C2: Discounted Cash Flow Valuation
C3: $ in millions except per share
C4: Most recent fiscal year end | G4: Discount rate (WACC) | I4: =F51 -> 0.12647402 | J4: Link from WACC
C5: End of first fiscal year | D5: 45897 | G5: Share price (Public Co) | I5: ='FSM Forecast'!D9 -> 895.88
C6: Most recent quarter end date | G6: Share price date | I6: ='FSM Forecast'!D8 -> 46168
C7: Valuation date | D7: 46168 | G7: Midyear adjustment? | I7: 1
C8: Portion of First Year Cash Flows | D8: =1-YEARFRAC(D7,D5) -> 0.25555556
G9: Case active: | H9: ='FSM Forecast'!D12 -> Base Case
B10: x | C10: Unlevered Free Cash Flows
C11: Fiscal year | E11: 2025 | F11: 2026 | G11: =F11+1 -> 2027 | H11: =G11+1 -> 2028 | I11: =H11+1 -> 2029 | J11: =I11+1 -> 2030
C12: Fiscal year end date | E12: =D5 -> 45897 | F12: =DATE(2025,8,28)+364 -> 46261 | G12: =DATE(2026,8,27)+364 -> 46625 | H12: =DATE(2027,8,26)+371 -> 46996 | I12: =DATE(2028,8,31)+364 -> 47360 | J12: =DATE(2029,8,30)+364 -> 47724
C14: Revenue | E14: ='FSM Forecast'!F18 -> 37378 | F14: ='FSM Forecast'!G18 -> 111252.28 | G14: ='FSM Forecast'!H18 -> 158866.68 | H14: ='FSM Forecast'!I18 -> 159891.88 | I14: ='FSM Forecast'!J18 -> 149898.64 | J14: ='FSM Forecast'!K18 -> 161890.53
C15: % growth | F15: =F14/E14-1 -> 1.9764108 | G15: =G14/F14-1 -> 0.42798579 | H15: =H14/G14-1 -> 0.0064531855 | I15: =I14/H14-1 -> -0.0625 | J15: =J14/I14-1 -> 0.08
C16: EBITDA | E16: =E18+E25 -> 9770 | F16: =F18+F25 -> 85908.354 | G16: =G18+G25 -> 131055.29 | H16: =H18+H25 -> 112304.96 | I16: =I18+I25 -> 93957.469 | J16: =J18+J25 -> 93048.686
C17: % margin | E17: =E16/E14 -> 0.2613837 | F17: =F16/F14 -> 0.77219407 | G17: =G16/G14 -> 0.8249388 | H17: =H16/H14 -> 0.70238064 | I17: =I16/I14 -> 0.6268067 | J17: =J16/J14 -> 0.57476301
C18: EBIT | E18: ='FSM Forecast'!F25 -> 9770 | F18: ='FSM Forecast'!G25 -> 70867.705 | G18: ='FSM Forecast'!H25 -> 108442.4 | H18: ='FSM Forecast'!I25 -> 85222.371 | I18: ='FSM Forecast'!J25 -> 64906.109 | J18: ='FSM Forecast'!K25 -> 62004.072
C19: % margin | E19: =E18/E14 -> 0.2613837 | F19: =F18/F14 -> 0.637 | G19: =G18/G14 -> 0.6826 | H19: =H18/H14 -> 0.533 | I19: =I18/I14 -> 0.433 | J19: =J18/J14 -> 0.383
C21: Tax on EBIT | E21: =E22*E18 -> 1137.5057 | F21: =F22*F18 -> 11693.171 | G21: =G22*G18 -> 17892.996 | H21: =H22*H18 -> 14061.691 | I21: =I22*I18 -> 10709.508 | J21: =J22*J18 -> 10230.672
C22: Tax rate | E22: ='FSM Forecast'!F44 -> 0.11642842 | F22: ='FSM Forecast'!G44 -> 0.165 | G22: ='FSM Forecast'!H44 -> 0.165 | H22: ='FSM Forecast'!I44 -> 0.165 | I22: ='FSM Forecast'!J44 -> 0.165 | J22: ='FSM Forecast'!K44 -> 0.165
C23: NOPAT (aka EBIAT) | E23: =E18*(1-E22) -> 8632.4943 | F23: =F18*(1-F22) -> 59174.534 | G23: =G18*(1-G22) -> 90549.402 | H23: =H18*(1-H22) -> 71160.68 | I23: =I18*(1-I22) -> 54196.601 | J23: =J18*(1-J22) -> 51773.4
C25: Depreciation & amortization | F25: ='FSM Forecast'!G33 -> 15040.649 | G25: ='FSM Forecast'!H33 -> 22612.893 | H25: ='FSM Forecast'!I33 -> 27082.589 | I25: ='FSM Forecast'!J33 -> 29051.36 | J25: ='FSM Forecast'!K33 -> 31044.614
C26: Changes in net working capital | F26: =F32 -> -17352.049 | G26: =G32 -> -11152.97 | H26: =H32 -> 1145.777 | I26: =I32 -> 3049.3449 | J26: =J32 -> -2090.5701
C27: Capital expenditures | F27: ='FSM Forecast'!G108 -> 26000 | G27: ='FSM Forecast'!H108 -> 36000 | H27: ='FSM Forecast'!I108 -> 40000 | I27: ='FSM Forecast'!J108 -> 40000 | J27: ='FSM Forecast'!K108 -> 40000
C28: as % of revenue | F28: =F27/F14 -> 0.23370307 | G28: =G27/G14 -> 0.2266051 | H28: =H27/H14 -> 0.25016905 | I28: =I27/I14 -> 0.26684699 | J28: =J27/J14 -> 0.24708055
C30: Unlevered free cash flows (UFCF) | F30: =F23+F25+F26+F27 -> 82863.134 | G30: =G23+G25+G26+G27 -> 138009.32 | H30: =H23+H25+H26+H27 -> 139389.05 | I30: =I23+I25+I26+I27 -> 126297.31 | J30: =J23+J25+J26+J27 -> 120727.44
C32: Net working capital (WC Assets - WC liabilities) | F32: ='FSM Forecast'!G86+'FSM Forecast'!G87 -> -17352.049 | G32: ='FSM Forecast'!H86+'FSM Forecast'!H87 -> -11152.97 | H32: ='FSM Forecast'!I86+'FSM Forecast'!I87 -> 1145.777 | I32: ='FSM Forecast'!J86+'FSM Forecast'!J87 -> 3049.3449 | J32: ='FSM Forecast'!K86+'FSM Forecast'!K87 -> -2090.5701
B33: x | C33: as % of revenue | F33: =F32/F14 -> -0.15597027 | G33: =G32/G14 -> -0.070203332 | H33: =H32/H14 -> 0.0071659485 | I33: =I32/I14 -> 0.020342713 | J33: =J32/J14 -> -0.01291348
C35: Weighted Average Cost of Capital
C37: Risk free rate (Rf) | F37: 0.04263
C38: Equity Beta | F38: 1.7
C39: Equity risk premium (Rm - Rf) | F39: 0.05
C40: Cost of Equity (Ke) | F40: =F37+F38*F39 -> 0.12763
C42: Cost of debt | F42: ='FSM Forecast'!G164 -> 0.0525
C43: Tax rate | F43: ='FSM Forecast'!G44 -> 0.165
C44: After-tax Cost of Debt (Kdt) | F44: =F42*(1-F43) -> 0.0438375
C46: Percentage of Capital
C47: Debt | E47: ='FSM Forecast'!G161+'FSM Forecast'!G157 -> 14067 | F47: =E47/E49 -> 0.01379575
C48: Equity | E48: ='FSM Forecast'!D11*I5 -> 1005594.8 | F48: =E48/E49 -> 0.98620425
C49: Total capital | E49: =SUM(E47:E48) -> 1019661.8 | F49: =SUM(F47:F48) -> 1
C51: Weighted Average Cost of Capital | F51: =F40*F48+F44*F47 -> 0.12647402
C53: ="Present value of UFCF on "&TEXT(D7,"mmm dd, yyyy")&" valuation date" -> Present value of UFCF on May 26, 2026 valuation date
E54: Val date | F54: Yr 1 - Stub | G54: Year 2 | H54: Year 3 | I54: Year 4 | J54: Year 5
C55: Date for discounting cash flows | E55: =D7 -> 46168 | F55: =IF($I$7=1,AVERAGE(F12,E55),F12) -> 46214.5 | G55: =IF($I$7=1,AVERAGE(F12,G12),G12) -> 46443 | H55: =IF($I$7=1,AVERAGE(G12,H12),H12) -> 46810.5 | I55: =IF($I$7=1,AVERAGE(H12,I12),I12) -> 47178 | J55: =IF($I$7=1,AVERAGE(I12,J12),J12) -> 47542
C56: Unlevered free cash flows (UFCF) stub adjusted | D56: =D8 -> 0.25555556 | F56: =F30*D56 -> 21176.134 | G56: =G30 -> 138009.32 | H56: =H30 -> 139389.05 | I56: =I30 -> 126297.31 | J56: =J30 -> 120727.44
C57: Present value of of unlevered free cash flows | F57: =F56/(1+$I$4)^((F55-$D$7)/365) -> 20857.274 | G57: =G56/(1+$I$4)^((G55-$D$7)/365) -> 126165.44 | H57: =H56/(1+$I$4)^((H55-$D$7)/365) -> 113027.78 | I57: =I56/(1+$I$4)^((I55-$D$7)/365) -> 90839.598 | J57: =J56/(1+$I$4)^((J55-$D$7)/365) -> 77109.457
C59: Terminal value - growth in perpetuity approach | F59: Terminal value - EBITDA multiple approach
C60: Long term growth rate | D60: 0.03 | F60: Terminal year EBITDA | J60: =J16 -> 93048.686
C61: =YEAR(J12)&" FCF x (1+g)" -> 2030 FCF x (1+g) | D61: =J56*(1+D60) -> 124349.27 | F61: EBITDA multiple | J61: 13
C62: ="Terminal value in "&YEAR(J12) -> Terminal value in 2030 | D62: =D61/(I4-D60) -> 1288940.5 | F62: ="Terminal value in "&YEAR(J12) -> Terminal value in 2030 | J62: =J60*J61 -> 1209632.9
C63: Present value of terminal value | D63: =D62/(1+I4)^((J12-$E$55)/365) -> 775791.04 | F63: Present value of terminal value | J63: =J62/(1+I4)^((J12-E55)/365) -> 728057.2
C64: Present value of stage 1 cash flows | D64: =SUM(F57:J57) -> 427999.55 | F64: Present value of stage 1 cash flows | J64: =D64 -> 427999.55
C65: Total enterprise value (TEV) | D65: =D64+D63 -> 1203790.6 | F65: Enterprise value (stage 1 + 2) | J65: =SUM(J63:J64) -> 1156056.7
C67: Terminal value as % of TEV | D67: =D63/$D$65 -> 0.64445681 | F67: Terminal value as % of TEV | J67: =+J63/J65 -> 0.62977635
C68: Stage 1 cash flows as % of TEV | D68: =1-D67 -> 0.35554319 | F68: Cash flows as % of TEV | J68: =1-J67 -> 0.37022365
C69: Implied TV exit EBITDA multiple | D69: =(D62/J16) -> 13.852323 | F69: Implied terminal growth rate | J69: =(I4-J56/J62)/(1+J56/J62) -> 0.024248838
C71: Net debt
C72: Source doc | D72: Micron Q2 2026 10-Q
C73: Source date | D73: =D7 -> 46168
C74: Gross debt and equivalents
C75: Debt | D75: 10059
C76: Convertible debt | D76: 0
C77: Preferred stock | D77: 0
C78: Noncontrolling (minority) interests | D78: 0
C79: Nonoperating assets
C80: Cash | D80: 16700
C81: Equity investments | D81: 183
B83: x | C83: Net debt | D83: =SUM(D75:D78)-SUM(D80:D81) -> -6824
C85: Net diluted shares outstanding | D85: ='FSM Forecast'!G180 -> 1124.7932
C87: Valuation
D88: Perpetuity | E88: EBITDA
C89: Enterprise value | D89: =D65 -> 1203790.6 | E89: =J65 -> 1156056.7
C90: Net debt | D90: =$D$83 -> -6824 | E90: =$D$83 -> -6824
C91: Equity value | D91: =D89-D90 -> 1210614.6 | E91: =E89-E90 -> 1162880.7
C92: Shares outstanding | D92: =$D$85 -> 1124.7932 | E92: =$D$85 -> 1124.7932
C93: Equity value per share | D93: =D91/D92 -> 1076.2997 | E93: =E91/E92 -> 1033.8618
D95: Last Twelve Months (LTM)
D96: Perpetuity | E96: EBITDA
C97: EV / Revenue | D97: =D89/$F$14 -> 10.820367 | E97: =E89/$F$14 -> 10.391308
C98: EV / EBITDA | D98: =D89/$F$16 -> 14.012497 | E98: =E89/$F$16 -> 13.456861
C99: EV / EBIT | D99: =D89/$F$18 -> 16.986448 | E99: =E89/$F$18 -> 16.312885
D100: Year 1
D101: Perpetuity | E101: EBITDA
C102: EV / Revenue | D102: =D89/$F$14 -> 10.820367 | E102: =E89/$F$14 -> 10.391308
C103: EV / EBITDA | D103: =D89/$F$16 -> 14.012497 | E103: =E89/$F$16 -> 13.456861
C104: EV / EBIT | D104: =D89/$F$18 -> 16.986448 | E104: =E89/$F$18 -> 16.312885
C106: Sensitivity Analysis
F108: Equity Value Per Share | N108: Year 1 EBITDA Multiple
F109: Long Term Growth Rate | N109: Long Term Growth Rate
E110: =D93 -> 1076.2997 | F110: =G110-0.005 -> 0.02 | G110: =H110-0.005 -> 0.025 | H110: 0.03 | I110: =H110+0.005 -> 0.035 | J110: =I110+0.005 -> 0.04 | M110: =D103 -> 14.012497 | N110: =O110-0.005 -> 0.02 | O110: =P110-0.005 -> 0.025 | P110: 0.03 | Q110: =P110+0.005 -> 0.035 | R110: =Q110+0.005 -> 0.04
E111: =E112+0.005 -> 0.136 | F111: 928.3945 | G111: 955.8875 | H111: 985.97417 | I111: 1019.0397 | J111: 1055.5496 | M111: =M112+0.005 -> 0.136 | N111: 12.075983 | O111: 12.435948 | P111: 12.829871 | Q111: 13.262796 | R111: 13.740818
E112: =E113+0.005 -> 0.131 | F112: 967.18582 | G112: 997.70868 | H112: 1031.2536 | I112: 1068.2928 | J112: 1109.4022 | M112: =M113+0.005 -> 0.131 | N112: 12.583876 | O112: 12.98351 | P112: 13.422712 | Q112: 13.907664 | R112: 14.445907
D113: WACC | E113: 0.126 | F113: 1009.6519 | G113: 1043.6853 | H113: 1081.2639 | I113: 1122.972 | J113: 1169.5299 | L113: WACC | M113: 0.126 | N113: 13.139882 | O113: 13.58548 | P113: 14.077494 | Q113: 14.623576 | R113: 15.233155
E114: =E113-0.005 -> 0.121 | F114: 1056.3399 | G114: 1094.4681 | H114: 1136.7863 | I114: 1184.0252 | J114: 1237.096 | M114: =M113-0.005 -> 0.121 | N114: 13.751165 | O114: 14.250376 | P114: 14.804445 | Q114: 15.422942 | R114: 16.117795
E115: 0.116 | F115: 1107.9107 | G115: 1150.8507 | H115: 1198.7837 | I115: 1252.6344 | J115: 1313.5706 | M115: 0.116 | N115: 14.426379 | O115: 14.98859 | P115: 15.616174 | Q115: 16.321238 | R115: 17.119073
F117: Equity Value Per Share | N117: Year 1 EBITDA Multiple
F118: Exit EBITDA Multiple | N118: Exit EBITDA Multiple
E119: =E93 -> 1033.8618 | F119: =G119-0.5 -> 12 | G119: =H119-0.5 -> 12.5 | H119: 13 | I119: =H119+0.5 -> 13.5 | J119: =I119+0.5 -> 14 | M119: =E103 -> 13.456861 | N119: =O119-0.5 -> 12 | O119: =P119-0.5 -> 12.5 | P119: 13 | Q119: =P119+0.5 -> 13.5 | R119: =Q119+0.5 -> 14
E120: =E121+0.005 -> 0.136 | F120: 956.79542 | G120: 980.81298 | H120: 1004.8305 | I120: 1028.8481 | J120: 1052.8657 | M120: =M121+0.005 -> 0.136 | N120: 12.447835 | O120: 12.762296 | P120: 13.076756 | Q120: 13.391217 | R120: 13.705677
E121: =E122+0.005 -> 0.131 | F121: 970.97165 | G121: 995.44513 | H121: 1019.9186 | I121: 1044.3921 | J121: 1068.8656 | M121: =M122+0.005 -> 0.131 | N121: 12.633444 | O121: 12.953874 | P121: 13.274303 | Q121: 13.594733 | R121: 13.915163
D122: WACC | E122: 0.126 | F122: 985.45782 | G122: 1010.3979 | H122: 1035.3381 | I122: 1060.2782 | J122: 1085.2183 | L122: WACC | M122: 0.126 | N122: 12.82311 | O122: 13.14965 | P122: 13.47619 | Q122: 13.802729 | R122: 14.129269
...
